{
    "uiExpiraionDate": "2021-03-19T14:52:13.000Z",
    "outageMapDataResponse": {
        "publishDate": "March 19, 2021, 07:37 AM",
        "AOCLocationStats": {
            "countyBlock": {
                "county": [
                    {
                        "countyName": "Los Angeles                             ",
                        "numberOfIncidents": "3",
                        "numberoOfCustomersAffected": "181",
                        "centroidX": "-118.351107325584",
                        "centroidY": "33.819720564505"
                    },
                    {
                        "countyName": "San Bernardino                          ",
                        "numberOfIncidents": "1",
                        "numberoOfCustomersAffected": "10",
                        "centroidX": "-116.176933512471",
                        "centroidY": "34.84217480790910"
                    }
                ],
                "countyTotals": {
                    "totalIncidents": "4",
                    "totalCustomersAffected": "191"
                }
            },
            "cityBlock": {
                "city": [
                    {
                        "cityName": "Alhambra",
                        "numberOfIncidents": "1",
                        "numberoOfCustomersAffected": "55",
                        "centroidX": "-118.135415990706",
                        "centroidY": "34.08398054930950"
                    },
                    {
                        "cityName": "South San Gabriel",
                        "numberOfIncidents": "1",
                        "numberoOfCustomersAffected": "90",
                        "centroidX": "-118.096175780145",
                        "centroidY": "34.04888973470150"
                    },
                    {
                        "cityName": "Unincorporated Area - Los Angeles County",
                        "numberOfIncidents": "1",
                        "numberoOfCustomersAffected": "36",
                        "centroidX": "-118.214453761165",
                        "centroidY": "34.41817081802910"
                    },
                    {
                        "cityName": "Unincorporated Area - San Bernardino County",
                        "numberOfIncidents": "1",
                        "numberoOfCustomersAffected": "10",
                        "centroidX": "-116.131102794254",
                        "centroidY": "34.86889126946560"
                    }
                ],
                "cityTotals": {
                    "totalIncidents": "4",
                    "totalCustomersAffected": "191"
                }
            },
            "zipCodeBlock": {
                "zipCode": [
                    {
                        "zipCodeName": "91770",
                        "numberOfIncidents": "1",
                        "numberoOfCustomersAffected": "90",
                        "centroidX": "-118.083585150474",
                        "centroidY": "34.06433973898590"
                    },
                    {
                        "zipCodeName": "91789",
                        "numberOfIncidents": "1",
                        "numberoOfCustomersAffected": "36",
                        "centroidX": "-117.853419332815",
                        "centroidY": "34.02100857812580"
                    },
                    {
                        "zipCodeName": "91801",
                        "numberOfIncidents": "1",
                        "numberoOfCustomersAffected": "55",
                        "centroidX": "-118.127955429106",
                        "centroidY": "34.09056318810640"
                    },
                    {
                        "zipCodeName": "No Zip Code",
                        "numberOfIncidents": "1",
                        "numberoOfCustomersAffected": "10",
                        "centroidX": "\n        ",
                        "centroidY": "\n        "
                    }
                ],
                "zipCodeTotals": {
                    "totalIncidents": "7",
                    "totalCustomersAffected": "372"
                }
            },
            "districtBlock": {
                "district": [
                    {
                        "districtNumber": "22",
                        "numberOfIncidents": "2",
                        "numberoOfCustomersAffected": "145",
                        "centroidX": "-118.095054626544",
                        "centroidY": "34.04492252099090"
                    },
                    {
                        "districtNumber": "26",
                        "numberOfIncidents": "1",
                        "numberoOfCustomersAffected": "36",
                        "centroidX": "-117.843448641056",
                        "centroidY": "34.13907182771690"
                    },
                    {
                        "districtNumber": "31",
                        "numberOfIncidents": "1",
                        "numberoOfCustomersAffected": "10",
                        "centroidX": "-117.064038478043",
                        "centroidY": "34.05116348904590"
                    }
                ],
                "districtTotals": {
                    "totalIncidents": "4",
                    "totalCustomersAffected": "191"
                }
            },
            "sectorBlock": {
                "sector": [
                    {
                        "sectorNumber": "MESA",
                        "numberOfIncidents": "2",
                        "numberoOfCustomersAffected": "145",
                        "centroidX": "-118.041625982422",
                        "centroidY": "34.18203233598380"
                    },
                    {
                        "sectorNumber": "MIRALOMA",
                        "numberOfIncidents": "1",
                        "numberoOfCustomersAffected": "36",
                        "centroidX": "-117.705783857999",
                        "centroidY": "34.047426553560"
                    },
                    {
                        "sectorNumber": "VISTA",
                        "numberOfIncidents": "1",
                        "numberoOfCustomersAffected": "10",
                        "centroidX": "-117.166920310144",
                        "centroidY": "34.11683585814790"
                    }
                ],
                "sectorTotals": {
                    "totalIncidents": "4",
                    "totalCustomersAffected": "191"
                }
            }
        },
        "AOCMacro": {
            "macro": []
        },
        "AOCIncidents": {
            "incident": [
                {
                    "incidentId": "123805360",
                    "incidentType": "PO",
                    "FACJobStatusCode": "D",
                    "OANNumber": "1154751",
                    "outageStartDateTime": "3/19/2021 4:00:00 AM",
                    "versionDate": "3/19/2021 7:26:21 AM",
                    "lastChangeDateTime": "3/19/2021 6:51:01 AM",
                    "estimateCLUDateTime": "3/19/2021 8:00:00 AM",
                    "memoCauseCode": "21",
                    "memoCauseCodeDescription": "Pole Upgrade",
                    "crewStatusCode": "04",
                    "crewStatusCodeDescription": "Work is in progress.",
                    "resultCode": "01",
                    "resultCodeDesription": "Enhancing Reliability",
                    "numberOfCustomersAffected": "10",
                    "zipCode": "No Zip Code",
                    "countyName": "San Bernardino                          ",
                    "cityName": "Unincorporated Area - San Bernardino County",
                    "districtNumber": "31",
                    "sectorNumber": "VISTA",
                    "ERTCode": "07",
                    "centroidX": "-116.981489",
                    "centroidY": "34.14892900000370"
                },
                {
                    "incidentId": "123807427",
                    "incidentType": "PO",
                    "FACJobStatusCode": "D",
                    "OANNumber": "1154987",
                    "outageStartDateTime": "3/19/2021 2:00:00 AM",
                    "versionDate": "3/19/2021 7:26:21 AM",
                    "lastChangeDateTime": "3/19/2021 6:03:39 AM",
                    "estimateCLUDateTime": "3/19/2021 10:00:00 AM",
                    "memoCauseCode": "21",
                    "memoCauseCodeDescription": "Pole Upgrade",
                    "crewStatusCode": "04",
                    "crewStatusCodeDescription": "Work is in progress.",
                    "resultCode": "01",
                    "resultCodeDesription": "Enhancing Reliability",
                    "numberOfCustomersAffected": "36",
                    "zipCode": "91789",
                    "countyName": "Los Angeles                             ",
                    "cityName": "Unincorporated Area - Los Angeles County",
                    "districtNumber": "26",
                    "sectorNumber": "MIRALOMA",
                    "ERTCode": "07",
                    "centroidX": "-117.871186182097",
                    "centroidY": "33.98820587710790"
                },
                {
                    "incidentId": "123886797",
                    "incidentType": "Not Available",
                    "FACJobStatusCode": "F",
                    "OANNumber": "1159755",
                    "outageStartDateTime": "3/18/2021 10:22:53 PM",
                    "versionDate": "3/19/2021 7:26:21 AM",
                    "lastChangeDateTime": "3/19/2021 7:13:21 AM",
                    "estimateCLUDateTime": "Most up by 3/19/2021 10:00:00 AM",
                    "memoCauseCode": "11",
                    "memoCauseCodeDescription": "Traffic Accident",
                    "crewStatusCode": "04",
                    "crewStatusCodeDescription": "Work is in progress.",
                    "resultCode": "06",
                    "resultCodeDesription": "Equipment Damage",
                    "numberOfCustomersAffected": "90",
                    "zipCode": "91770",
                    "countyName": "Los Angeles                             ",
                    "cityName": "South San Gabriel",
                    "districtNumber": "22",
                    "sectorNumber": "MESA",
                    "ERTCode": "05",
                    "centroidX": "-118.099966804569",
                    "centroidY": "34.05157515363930"
                },
                {
                    "incidentId": "123887324",
                    "incidentType": "Not Available",
                    "FACJobStatusCode": "F",
                    "OANNumber": "1159786",
                    "outageStartDateTime": "3/19/2021 4:57:17 AM",
                    "versionDate": "3/19/2021 7:26:21 AM",
                    "lastChangeDateTime": "3/19/2021 7:21:48 AM",
                    "estimateCLUDateTime": "Not Available",
                    "memoCauseCode": "16",
                    "memoCauseCodeDescription": "Equipment Problems",
                    "crewStatusCode": "11",
                    "crewStatusCodeDescription": "We have identified the problem and are working to restore your service.",
                    "resultCode": "0",
                    "resultCodeDesription": "Not Available",
                    "numberOfCustomersAffected": "55",
                    "zipCode": "91801",
                    "countyName": "Los Angeles                             ",
                    "cityName": "Alhambra",
                    "districtNumber": "22",
                    "sectorNumber": "MESA",
                    "ERTCode": "2",
                    "centroidX": "-118.108916984083",
                    "centroidY": "34.08253633465490"
                }
            ]
        }
    }
}
